easy_start_device/__init__.py
easy_start_device/tjbrhk.py
easy_start_device-0.1.4.dist-info/licenses/LICENSE
easy_start_device-0.1.4.dist-info/METADATA
easy_start_device-0.1.4.dist-info/WHEEL
easy_start_device-0.1.4.dist-info/top_level.txt
easy_start_device-0.1.4.dist-info/RECORD
